{
  "customers": [
    {
      "id": 1,
      "name": "Tuấn Anh HIhi",
      "birthDate": "2000-12-12",
      "idCard": "123456789",
      "phone": "0948123123",
      "email": "anh1910@gmail.com",
      "address": "Quang Tri",
      "typeCustomer": {
        "id": 2,
        "nameTypeCustomer": "Platinum"
      }
    },
    {
      "id": 2,
      "typeCustomer": {
        "id": 1,
        "nameTypeCustomer": "Gold"
      },
      "name": "Tân",
      "birthDate": "2000-10-10",
      "idCard": "312654978",
      "phone": "0948456456",
      "email": "tan1010@gmail.com",
      "address": "Đà Nẵng"
    },
    {
      "id": 3,
      "typeCustomer": {
        "id": 1,
        "nameTypeCustomer": "Gold"
      },
      "name": "Trí",
      "birthDate": "2013-10-10",
      "idCard": "741852963",
      "phone": "0945123456",
      "email": "tri2013@gmail.com",
      "address": "Nghệ An"
    },
    {
      "name": "Hoàng Anh",
      "birthDate": "2000-12-12",
      "idCard": "123123123",
      "phone": "0948123361",
      "email": "anhzxczxct@gmail.com",
      "address": "Đà Nẵng",
      "typeCustomer": {
        "id": 1,
        "nameTypeCustomer": "Gold"
      },
      "id": 4
    }
  ],
  "typeCustomers": [
    {
      "id": 1,
      "nameTypeCustomer": "Gold"
    },
    {
      "id": 2,
      "nameTypeCustomer": "Platinum"
    },
    {
      "id": 3,
      "nameTypeCustomer": "Silver"
    }
  ]
}